gnome_pomodoro_client/__main__.py
gnome_pomodoro_client/api.py
gnome_pomodoro_client-0.1.2.dist-info/entry_points.txt
gnome_pomodoro_client-0.1.2.dist-info/WHEEL
gnome_pomodoro_client-0.1.2.dist-info/METADATA
gnome_pomodoro_client-0.1.2.dist-info/RECORD
